CHANGES.rst
LICENSE.txt
MANIFEST.in
README.rst
setup.py
src/remove_hairs/__init__.py
src/remove_hairs.egg-info/PKG-INFO
src/remove_hairs.egg-info/SOURCES.txt
src/remove_hairs.egg-info/dependency_links.txt
src/remove_hairs.egg-info/requires.txt
src/remove_hairs.egg-info/top_level.txt
src/remove_hairs.egg-info/zip-safe
tests/test_remove_hairs.py